box/__init__.py
box/box.py
box/box_iterator.py
box/branch_node.py
box/break_node.py
box/continue_node.py
box/for_each_node.py
box/for_loop_node.py
box/function_call_node.py
box/function_declaration_node.py
box/generator.py
box/importer.py
box/main.py
box/operator_node.py
box/parser.py
box/return_node.py
box/set_node.py
box/token.py
box/while_loop_node.py
boxlang-0.1.1.dist-info/LICENSE
boxlang-0.1.1.dist-info/METADATA
boxlang-0.1.1.dist-info/WHEEL
boxlang-0.1.1.dist-info/entry_points.txt
boxlang-0.1.1.dist-info/top_level.txt
boxlang-0.1.1.dist-info/RECORD
