Metadata-Version: 2.1
Name: boxlang
Version: 0.1.1
Summary: Box is a text-based visual programming language inspired by Unreal Engine blueprint function graphs.
Home-page: https://github.com/p-ranav/box
Author: Pranav Srinivas Kumar
Author-email: pranav.srinivas.kumar@gmail.com
License: UNKNOWN
Project-URL: Bug Tracker, https://github.com/p-ranav/box/issues
Platform: UNKNOWN
Classifier: Programming Language :: Python :: 3
Classifier: License :: OSI Approved :: MIT License
Classifier: Operating System :: OS Independent
Requires-Python: >=3.5
License-File: LICENSE
